doc_transform/__init__.py
doc_transform-0.0.1.dist-info/LICENSE
doc_transform-0.0.1.dist-info/METADATA
doc_transform-0.0.1.dist-info/WHEEL
doc_transform-0.0.1.dist-info/top_level.txt
doc_transform-0.0.1.dist-info/zip-safe
doc_transform-0.0.1.dist-info/RECORD
